vinterunofficial/__init__.py
vinterunofficial/config.py
vinterunofficial/utils.py
vinterunofficial/vinter_abc.py
vinterunofficial/vinter_sdk.py
vinterunofficial/vinter_sdk_async.py
vinterunofficial/vinter_sdk_ws.py
vinterunofficial-0.1.9.dist-info/METADATA
vinterunofficial-0.1.9.dist-info/WHEEL
vinterunofficial-0.1.9.dist-info/top_level.txt
vinterunofficial-0.1.9.dist-info/RECORD
