Metadata-Version: 2.1
Name: vinterunofficial
Version: 0.1.9
Project-URL: homepage, https://rahulmistri1997.github.io/vinterunofficial-pypi
Project-URL: documentation, https://rahulmistri1997.github.io/vinterunofficial-pypi
Project-URL: repository, https://github.com/rahulmistri1997/vinterunofficial-pypi
Requires-Dist: httpx >=0.23.3
Requires-Dist: websocket-client >=1.5.1
